NumPlateVision/__init__.py
NumPlateVision/character_extractor.py
NumPlateVision/number_plate_extractor.py
NumPlateVision/number_plate_reader.py
NumPlateVision/model/__init__.py
NumPlateVision/model/character_recognition_model.h5
tests/__init__.py
tests/test.py
NumPlateVision-0.1.3.dist-info/METADATA
NumPlateVision-0.1.3.dist-info/WHEEL
NumPlateVision-0.1.3.dist-info/top_level.txt
NumPlateVision-0.1.3.dist-info/RECORD
