Metadata-Version: 2.1
Name: NumPlateVision
Version: 0.1.3
Summary: Extracting a number plate from an image and recognising the characters on them
Home-page: https://github.com/elliottcoops/Number-Plate-Recognition
Author: Elliott Cooper
Author-email: elliottcoops@gmail.com
Requires-Python: >=3.11
Requires-Dist: numpy>=1.26.4
Requires-Dist: keras==3.5.0
Requires-Dist: opencv-python>=4.10.0.84
Requires-Dist: tensorflow>=2.17.0
Requires-Dist: torch>=2.4.0
Requires-Dist: pillow>=10.4.0
Requires-Dist: transformers>=4.44.0
